python_bubble_sort/__init__.py
python_bubble_sort/bubble_sort.py
python_bubble_sort-1.0.0.dist-info/METADATA
python_bubble_sort-1.0.0.dist-info/WHEEL
python_bubble_sort-1.0.0.dist-info/top_level.txt
python_bubble_sort-1.0.0.dist-info/RECORD
